disrupt_idx/__init__.py
disrupt_idx/core.py
disrupt_idx-0.1.0.dist-info/METADATA
disrupt_idx-0.1.0.dist-info/WHEEL
disrupt_idx-0.1.0.dist-info/top_level.txt
disrupt_idx-0.1.0.dist-info/RECORD
