Metadata-Version: 2.4
Name: disrupt_idx
Version: 0.1.0
Summary: A comprehensive toolkit for calculating disruptive innovation metrics (DI1, DI5, mCD).
Author-email: Your Name <your@email.com>
Project-URL: Homepage, https://github.com/yourusername/repo
Classifier: Programming Language :: Python :: 3
Classifier: License :: OSI Approved :: MIT License
Classifier: Operating System :: OS Independent
Requires-Python: >=3.6
Requires-Dist: pandas>=1.0.0
Requires-Dist: tqdm>=4.0.0
